.gitignore
MANIFEST.in
README.rst
setup.py
pygments_style_monokailight/__init__.py
pygments_style_monokailight/monokailight.py
pygments_style_monokailight.egg-info/PKG-INFO
pygments_style_monokailight.egg-info/SOURCES.txt
pygments_style_monokailight.egg-info/dependency_links.txt
pygments_style_monokailight.egg-info/entry_points.txt
pygments_style_monokailight.egg-info/not-zip-safe
pygments_style_monokailight.egg-info/requires.txt
pygments_style_monokailight.egg-info/top_level.txt