Metadata-Version: 1.1
Name: pygments-style-monokailight
Version: 0.4
Summary: Pygments version of the monokai theme for light backgrounds.
Home-page: https://github.com/mlgill/pygments-style-monokailight
Author: Michelle Gill
Author-email: michelle@michellelynngill.com
License: MIT
Keywords: pygments,style,monokai,syntax highlighting
Platform: UNKNOWN
Classifier: Development Status :: 4 - Beta
Classifier: Environment :: Plugins
Classifier: Intended Audience :: Developers
Classifier: License :: OSI Approved :: MIT License
Classifier: Operating System :: OS Independent
Classifier: Programming Language :: Python
Classifier: Programming Language :: Python :: 2
Classifier: Topic :: Software Development :: Libraries :: Python Modules
